kleenscan/__init__.py
kleenscan/cli.py
kleenscan/kleenscan.py
kleenscan/lib/__init__.py
kleenscan/lib/cli_colors.py
kleenscan/lib/config.py
kleenscan/lib/errors.py
kleenscan/lib/files.py
kleenscan/lib/formatting.py
kleenscan/lib/helpers.py
kleenscan/lib/http.py
kleenscan/lib/log_configure.py
kleenscan-0.6.0.dist-info/METADATA
kleenscan-0.6.0.dist-info/WHEEL
kleenscan-0.6.0.dist-info/entry_points.txt
kleenscan-0.6.0.dist-info/top_level.txt
kleenscan-0.6.0.dist-info/RECORD
