Metadata-Version: 2.1
Name: kleenscan
Version: 0.6.0
Summary: Kleenscan command line application and API wrapper library.
Home-page: https://github.com/ksdev01/kleenscan-cli
Author: Kleenscan
Author-email: ksdev01@gmail.com
Classifier: Programming Language :: Python :: 3
Classifier: License :: OSI Approved :: MIT License
Classifier: Operating System :: OS Independent
Requires-Python: >=3.6
Requires-Dist: toml
Requires-Dist: pyyaml
Requires-Dist: requests
Requires-Dist: sty
